pysolotools_fiftyone/__init__.py
pysolotools_fiftyone/bounding_box_3d.py
pysolotools_fiftyone/exr_utils.py
pysolotools_fiftyone/solo_fiftyone.py
pysolotools_fiftyone-0.3.25.dist-info/LICENSE.md
pysolotools_fiftyone-0.3.25.dist-info/METADATA
pysolotools_fiftyone-0.3.25.dist-info/WHEEL
pysolotools_fiftyone-0.3.25.dist-info/entry_points.txt
pysolotools_fiftyone-0.3.25.dist-info/top_level.txt
pysolotools_fiftyone-0.3.25.dist-info/RECORD
