Metadata-Version: 2.1
Name: pysolotools-fiftyone
Version: 0.3.25
Summary: Voxel fiftyone integration for SOLO
Home-page: https://https://github.com/Unity-Technologies/pysolotools-fiftyone
Author: Unity Technologies
Author-email: computer-vision@unity3d.com
License: MIT
Classifier: License :: OSI Approved :: MIT License
Classifier: Programming Language :: Python
Classifier: Programming Language :: Python :: 3
Classifier: Programming Language :: Python :: 3.8
Requires-Python: >=3.8
License-File: LICENSE.md
Requires-Dist: fiftyone (>0.17.0)
Requires-Dist: setuptools (>=59.1.1)
Requires-Dist: pytest (>=6.2.2)
Requires-Dist: pytest-cov (>=3.0.0)
Requires-Dist: numpy (~=1.23.2)
Requires-Dist: openexr (>=1.3.8)
Requires-Dist: pillow (>=9.0.1)
Requires-Dist: pyquaternion (>=0.9.9)
Requires-Dist: pysolotools (>=0.3.17)
